setup.cfg
setup.py
kclboot/__init__.py
kclboot/bootstrapper.py
kclboot/command.py
kclboot/maven_jar.py
kclboot.egg-info/PKG-INFO
kclboot.egg-info/SOURCES.txt
kclboot.egg-info/dependency_links.txt
kclboot.egg-info/entry_points.txt
kclboot.egg-info/top_level.txt