Metadata-Version: 1.1
Name: kclboot
Version: 0.0.2
Summary: Unofficial AWS Kinesis Client Library Bootstrapper
Home-page: https://github.com/nivardus/kclboot
Author: Bennett Goble
Author-email: bennettgoble@gmail.com
License: MIT
Download-URL: https://github.com/nivardus/kclboot/tarball/0.0.1
Keywords: aws amazon kinesis
Platform: UNKNOWN
Classifier: Development Status :: 2 - Pre-Alpha
Classifier: Intended Audience :: Developers
Classifier: Intended Audience :: System Administrators
Classifier: Natural Language :: English
Classifier: License :: OSI Approved :: MIT License
Classifier: Programming Language :: Python :: 3 :: Only
